setup.py
envvars/__init__.py
envvars.egg-info/PKG-INFO
envvars.egg-info/SOURCES.txt
envvars.egg-info/dependency_links.txt
envvars.egg-info/top_level.txt