Metadata-Version: 1.1
Name: envvars
Version: 0.1.0
Summary: Get and Set environment variables using .env file
Home-page: http://github.com/mattseymour/python-envvars
Author: Matt Seymour
Author-email: matt@mattseymour.net
License: MIT
Platform: UNKNOWN
Classifier: Development Status :: 5 - Production/Stable
Classifier: Intended Audience :: Developers
Classifier: License :: OSI Approved :: MIT License
Classifier: Natural Language :: English
Classifier: Programming Language :: Python :: 2
Classifier: Programming Language :: Python :: 2.6
Classifier: Programming Language :: Python :: 2.7
Classifier: Programming Language :: Python :: 3
Classifier: Programming Language :: Python :: 3.3
Classifier: Programming Language :: Python :: 3.4
